{
  "title": {
    "en": "Change current to...",
    "nl": "Amperage veranderen naar..."
  },
  "titleformatted": {
    "en": "Change current to [[action_amps]]",
    "nl": "Amperage veranderen naar [[action_amps]]"
  },
  "args": [
    {
      "type": "device",
      "name": "device",
      "filter": "driver_id=go-eCharger_V1|go-eCharger_V2|go-eCharger_V3|go-eCharger_V4"
    },
    {
      "name": "action_amps",
      "type": "dropdown",
      "values": [
        { "id": "6", "label": { "en": "6 A" } },
        { "id": "10", "label": { "en": "10 A" } },
        { "id": "16", "label": { "en": "16 A" } },
        { "id": "32", "label": { "en": "32 A" } }
      ]
    }
  ]
}