{
  "title": {
    "en": "Change current limit to ",
    "nl": "Ampèrelimiet veranderen naar "
  },
  "titleFormatted": {
    "en": "Change current limit to [[action_amps]]",
    "nl": "Wijzig de ampèrelimiet in [[action_amps]]"
  },
  "hint": {
    "en": "Change the current limit in amperes for charging.",
    "nl": "Wijzig de ampèrelimiet in ampère voor opladen."
  },
  "args": [
    {
      "type": "device",
      "name": "device",
      "filter": "driver_id=go-eCharger_V1|go-eCharger_V2|go-eCharger_V3|go-eCharger_V4"
    },
    {
      "type": "range",
      "name": "action_amps",
      "title": {
        "en": "Current limit in amperes",
        "nl": "Ampèrelimiet in ampère"
      },
      "min": 6,
      "max": 32,
      "step": 2,
      "label": "A",
      "labelDecimals": 0
    }
  ],
  "tokens": [
    {
      "name": "amps",
      "type": "number",
      "title": {
        "en": "Amperes (A)",
        "nl": "Ampère (A)"
      }
    }
  ]

}